MANIFEST.in
README.md
requirements.txt
setup.cfg
setup.py
cave/__init__.py
cave/__version__.py
cave/cave_cli.py
cave/cavefacade.py
cave.egg-info/PKG-INFO
cave.egg-info/SOURCES.txt
cave.egg-info/dependency_links.txt
cave.egg-info/entry_points.txt
cave.egg-info/requires.txt
cave.egg-info/top_level.txt
cave/analyzer/__init__.py
cave/analyzer/base_analyzer.py
cave/analyzer/apt/__init__.py
cave/analyzer/apt/apt_overview.py
cave/analyzer/apt/apt_tensorboard.py
cave/analyzer/apt/loss_curves.py
cave/analyzer/budgets/__init__.py
cave/analyzer/budgets/bohb_learning_curves.py
cave/analyzer/budgets/budget_correlation.py
cave/analyzer/budgets/incumbents_over_budgets.py
cave/analyzer/configurator/__init__.py
cave/analyzer/configurator/configurator_footprint.py
cave/analyzer/configurator/parallel_coordinates.py
cave/analyzer/feature_analysis/__init__.py
cave/analyzer/feature_analysis/box_violin.py
cave/analyzer/feature_analysis/feature_analysis.py
cave/analyzer/feature_analysis/feature_clustering.py
cave/analyzer/feature_analysis/feature_correlation.py
cave/analyzer/feature_analysis/feature_importance.py
cave/analyzer/parameter_importance/__init__.py
cave/analyzer/parameter_importance/ablation.py
cave/analyzer/parameter_importance/base_parameter_importance.py
cave/analyzer/parameter_importance/fanova.py
cave/analyzer/parameter_importance/forward_selection.py
cave/analyzer/parameter_importance/local_parameter_importance.py
cave/analyzer/parameter_importance/pimp_comparison_table.py
cave/analyzer/performance/__init__.py
cave/analyzer/performance/algorithm_footprint.py
cave/analyzer/performance/compare_default_incumbent.py
cave/analyzer/performance/cost_over_time.py
cave/analyzer/performance/overview_table.py
cave/analyzer/performance/performance_table.py
cave/analyzer/performance/plot_ecdf.py
cave/analyzer/performance/plot_scatter.py
cave/html/__init__.py
cave/html/html_builder.py
cave/html/html_helpers.py
cave/html/web_files/css/accordion.css
cave/html/web_files/css/back-to-top.css
cave/html/web_files/css/bokeh-1.1.0.min.css
cave/html/web_files/css/bokeh-tables-1.1.0.min.css
cave/html/web_files/css/bokeh-widgets-1.1.0.min.css
