Metadata-Version: 1.1
Name: cave
Version: 1.4.1
Summary: CAVE, an analyzing tool for configuration optimizers
Home-page: https://github.com/automl/CAVE
Author: Marius Lindauer, Joshua Marben, Andre Biedenkapp
Author-email: biedenka@cs.uni-freiburg.de
License: 3-clause BSD
Keywords: machine learning algorithm configuration hyperparameter optimization tuning analyzing analysis visualization
Platform: Linux
Classifier: Development Status :: 5 - Production/Stable
Classifier: Topic :: Utilities
Classifier: Topic :: Scientific/Engineering
Classifier: Topic :: Scientific/Engineering :: Artificial Intelligence
Classifier: License :: OSI Approved :: BSD License
